{
    "users": {
        "user0": {
            "uid": "AgVRquyOPkMNSxP1nqNhRz0ro8l1",
            "name": "Sharon",
            "imageURL": "https://encrypted-tbn0.gstatic.com/images?q=tbn:ANd9GcTG0XOQJZDmLFBtubVdF_0Cp7BAD9Y5_pazDwkwD5O90JoCnh-l",
            "username": "a"
        },
        "user1": {
            "uid": "Xo740wrxJHeybp7Qjk6Ax73AXzi1",
            "name": "Anessa",
            "imageURL": "https://www.hearingdogs.org.uk/globalassets/sponsor/jade/sponsor-hearing-dog-puppy-jade-280-x-2413.jpg",
            "username": "b"
        },
        "user2": {
            "uid": "U4araoq24xMec8ukza0CFjznkvl2",
            "name": "Andrea",
            "imageURL": "https://yt3.ggpht.com/-V92UP8yaNyQ/AAAAAAAAAAI/AAAAAAAAAAA/zOYDMx8Qk3c/s900-c-k-no-mo-rj-c0xffffff/photo.jpg",
            "username": "c"
        },
        "user3": {
            "uid": "oWJ7aGqItdRnfwtKSPlpdr4HI5K2",
            "name": "Heather",
            "imageURL": "http://az616578.vo.msecnd.net/files/2016/12/05/636165548735526608-1767013013_tumblr_static_19835-red-panda-1920x1200-animal-wallpaper.jpg",
            "username": "d"
        }
    },
    "boards": {
        "board0": {
            "uid": "AgVRquyOPkMNSxP1nqNhRz0ro8l1",
            "title": "What",
            "description": "Whatevs",
            "timestamp": "tba"
        },
        "board1": {
            "uid": "AgVRquyOPkMNSxP1nqNhRz0ro8l1",
            "title": "Factals",
            "description": "Fractals",
            "timestamp": "tba"
        },
        "board2": {
            "uid": "Xo740wrxJHeybp7Qjk6Ax73AXzi1",
            "title": "Kites",
            "description": "Coolest kites ever",
            "timestamp": "tba"
        },
        "board3": {
            "uid": "Xo740wrxJHeybp7Qjk6Ax73AXzi1",
            "title": "Storms",
            "description": "Weather watching",
            "timestamp": "tba"
        },
        "board4": {
            "uid": "U4araoq24xMec8ukza0CFjznkvl2",
            "title": "Cookies!",
            "description": "I want to eat all the cookies!",
            "timestamp": "tba"
        },
        "board5": {
            "uid": "U4araoq24xMec8ukza0CFjznkvl2",
            "title": "Cakes!",
            "description": "Let them eat cake!",
            "timestamp": "tba"
        },
        "board6": {
            "uid": "oWJ7aGqItdRnfwtKSPlpdr4HI5K2",
            "title": "Kittens",
            "description": "Mew Mew Mew!",
            "timestamp": "tba"
        },
        "board7": {
            "uid": "oWJ7aGqItdRnfwtKSPlpdr4HI5K2",
            "title": "Mittens",
            "description": "Eep Eep!",
            "timestamp": "tba"
        }
    },
    "pins": {
        "pin00": {
            "uid": "AgVRquyOPkMNSxP1nqNhRz0ro8l1",
            "boardid": "board0",
            "URL": " https://encrypted-tbn0.gstatic.com/images?q=tbn:ANd9GcRmGvyR8yMsNJ_G6BM3vQNxbuQdBC6HNGd0-fv2R0XqRwON_myJzw",
            "imageURL": " https://encrypted-tbn0.gstatic.com/images?q=tbn:ANd9GcRmGvyR8yMsNJ_G6BM3vQNxbuQdBC6HNGd0-fv2R0XqRwON_myJzw",
            "title": "rainbowed fractal",
            "description": "rainbowed fractal",
            "timestamp": "tba"
        },
        "pin01": {
            "uid": "AgVRquyOPkMNSxP1nqNhRz0ro8l1",
            "boardid": "board0",
            "URL": "https://s-media-cache-ak0.pinimg.com/736x/c3/e7/27/c3e72742dfb048835c8389720942affe.jpg",
            "imageURL": "https://s-media-cache-ak0.pinimg.com/736x/c3/e7/27/c3e72742dfb048835c8389720942affe.jpg",
            "title": "umbrella fractal",
            "description": "umbrella fractal",
            "timestamp": "tba"
        },
        "pin02": {
            "uid": "AgVRquyOPkMNSxP1nqNhRz0ro8l1",
            "boardid": "board0",
            "URL": "https://encrypted-tbn0.gstatic.com/images?q=tbn:ANd9GcRZvV4XaDg56nl0FgEOcZinEd5H7cnCxJ7tp_p8ts0-VrLKOih3",
            "imageURL": "https://encrypted-tbn0.gstatic.com/images?q=tbn:ANd9GcRZvV4XaDg56nl0FgEOcZinEd5H7cnCxJ7tp_p8ts0-VrLKOih3",
            "title": "snow fractal",
            "description": "snow fractal",
            "timestamp": "tba"
        },
        "pin03": {
            "uid": "AgVRquyOPkMNSxP1nqNhRz0ro8l1",
            "boardid": "board0",
            "URL": "https://encrypted-tbn0.gstatic.com/images?q=tbn:ANd9GcRhRjBlxlj6v3pqzzfAcvPaLXASrmbWhZAYuTNSqrOpLg5z8NHG",
            "imageURL": "https://encrypted-tbn0.gstatic.com/images?q=tbn:ANd9GcRhRjBlxlj6v3pqzzfAcvPaLXASrmbWhZAYuTNSqrOpLg5z8NHG",
            "title": "web fractal",
            "description": "web fractal",
            "timestamp": "tba"
        },
        "pin04": {
            "uid": "AgVRquyOPkMNSxP1nqNhRz0ro8l1",
            "boardid": "board1",
            "URL": " https://encrypted-tbn0.gstatic.com/images?q=tbn:ANd9GcRmGvyR8yMsNJ_G6BM3vQNxbuQdBC6HNGd0-fv2R0XqRwON_myJzw",
            "imageURL": " https://encrypted-tbn0.gstatic.com/images?q=tbn:ANd9GcRmGvyR8yMsNJ_G6BM3vQNxbuQdBC6HNGd0-fv2R0XqRwON_myJzw",
            "title": "rainbowed fractal",
            "description": "rainbowed fractal",
            "timestamp": "tba"
        },
        "pin05": {
            "uid": "AgVRquyOPkMNSxP1nqNhRz0ro8l1",
            "boardid": "board1",
            "URL": "https://s-media-cache-ak0.pinimg.com/736x/c3/e7/27/c3e72742dfb048835c8389720942affe.jpg",
            "imageURL": "https://s-media-cache-ak0.pinimg.com/736x/c3/e7/27/c3e72742dfb048835c8389720942affe.jpg",
            "title": "umbrella fractal",
            "description": "umbrella fractal",
            "timestamp": "tba"
        },
        "pin06": {
            "uid": "AgVRquyOPkMNSxP1nqNhRz0ro8l1",
            "boardid": "board1",
            "URL": "https://encrypted-tbn0.gstatic.com/images?q=tbn:ANd9GcRZvV4XaDg56nl0FgEOcZinEd5H7cnCxJ7tp_p8ts0-VrLKOih3",
            "imageURL": "https://encrypted-tbn0.gstatic.com/images?q=tbn:ANd9GcRZvV4XaDg56nl0FgEOcZinEd5H7cnCxJ7tp_p8ts0-VrLKOih3",
            "title": "snow fractal",
            "description": "snow fractal",
            "timestamp": "tba"
        },
        "pin07": {
            "uid": "AgVRquyOPkMNSxP1nqNhRz0ro8l1",
            "boardid": "board1",
            "URL": "https://encrypted-tbn0.gstatic.com/images?q=tbn:ANd9GcRhRjBlxlj6v3pqzzfAcvPaLXASrmbWhZAYuTNSqrOpLg5z8NHG",
            "imageURL": "https://encrypted-tbn0.gstatic.com/images?q=tbn:ANd9GcRhRjBlxlj6v3pqzzfAcvPaLXASrmbWhZAYuTNSqrOpLg5z8NHG",
            "title": "web fractal",
            "description": "web fractal",
            "timestamp": "tba"
        },
        "pin08": {
            "uid": "Xo740wrxJHeybp7Qjk6Ax73AXzi1",
            "boardid": "board2",
            "URL": "https://s-media-cache-ak0.pinimg.com/736x/79/d9/86/79d9862fb655c3c15a80078197bfa88f.jpg",
            "imageURL": "https://s-media-cache-ak0.pinimg.com/736x/79/d9/86/79d9862fb655c3c15a80078197bfa88f.jpg",
            "title": "Bug Kite",
            "description": "this guy is CRAZY!",
            "timestamp": "tba"
        },
        "pin09": {
            "uid": "Xo740wrxJHeybp7Qjk6Ax73AXzi1",
            "boardid": "board2",
            "URL": "http://www.gkites.com/update/389-6.JPG",
            "imageURL": "http://www.gkites.com/update/389-6.JPG",
            "title": "Puppy Kites",
            "description": "lyk no wayz omg",
            "timestamp": "tba"
        },
        "pin10": {
            "uid": "Xo740wrxJHeybp7Qjk6Ax73AXzi1",
            "boardid": "board2",
            "URL": "https://s-media-cache-ak0.pinimg.com/originals/ea/7e/22/ea7e2227edf4f2bd57379359aca731b4.jpg",
            "imageURL": "https://s-media-cache-ak0.pinimg.com/originals/ea/7e/22/ea7e2227edf4f2bd57379359aca731b4.jpg",
            "title": "purple lightning",
            "description": "scary pic of purple lightning (my fav color)",
            "timestamp": "tba"
        },
        "pin11": {
            "uid": "Xo740wrxJHeybp7Qjk6Ax73AXzi1",
            "boardid": "board2",
            "URL": "https://dsx.weather.com//util/image/w/ef25fec9-b90d-4368-bb41-1da03aa2fe8e.jpg?v=at&w=1280&h=720&api=7db9fe61-7414-47b5-9871-e17d87b8b6a0",
            "imageURL": "https://dsx.weather.com//util/image/w/ef25fec9-b90d-4368-bb41-1da03aa2fe8e.jpg?v=at&w=1280&h=720&api=7db9fe61-7414-47b5-9871-e17d87b8b6a0",
            "title": "tree in the wind",
            "description": "wouldn't wanna be this guy!",
            "timestamp": "tba"
        },
        "pin12": {
            "uid": "Xo740wrxJHeybp7Qjk6Ax73AXzi1",
            "boardid": "board3",
            "URL": "https://s-media-cache-ak0.pinimg.com/736x/79/d9/86/79d9862fb655c3c15a80078197bfa88f.jpg",
            "imageURL": "https://s-media-cache-ak0.pinimg.com/736x/79/d9/86/79d9862fb655c3c15a80078197bfa88f.jpg",
            "title": "Bug Kite",
            "description": "this guy is CRAZY!",
            "timestamp": "tba"
        },
        "pin13": {
            "uid": "Xo740wrxJHeybp7Qjk6Ax73AXzi1",
            "boardid": "board3",
            "URL": "http://www.gkites.com/update/389-6.JPG",
            "imageURL": "http://www.gkites.com/update/389-6.JPG",
            "title": "Puppy Kites",
            "description": "lyk no wayz omg",
            "timestamp": "tba"
        },
        "pin14": {
            "uid": "Xo740wrxJHeybp7Qjk6Ax73AXzi1",
            "boardid": "board3",
            "URL": "https://s-media-cache-ak0.pinimg.com/originals/ea/7e/22/ea7e2227edf4f2bd57379359aca731b4.jpg",
            "imageURL": "https://s-media-cache-ak0.pinimg.com/originals/ea/7e/22/ea7e2227edf4f2bd57379359aca731b4.jpg",
            "title": "purple lightning",
            "description": "scary pic of purple lightning (my fav color)",
            "timestamp": "tba"
        },
        "pin15": {
            "uid": "Xo740wrxJHeybp7Qjk6Ax73AXzi1",
            "boardid": "board3",
            "URL": "https://dsx.weather.com//util/image/w/ef25fec9-b90d-4368-bb41-1da03aa2fe8e.jpg?v=at&w=1280&h=720&api=7db9fe61-7414-47b5-9871-e17d87b8b6a0",
            "imageURL": "https://dsx.weather.com//util/image/w/ef25fec9-b90d-4368-bb41-1da03aa2fe8e.jpg?v=at&w=1280&h=720&api=7db9fe61-7414-47b5-9871-e17d87b8b6a0",
            "title": "tree in the wind",
            "description": "wouldn't wanna be this guy!",
            "timestamp": "tba"
        },
        "pin16": {
            "uid": "U4araoq24xMec8ukza0CFjznkvl2",
            "boardid": "board4",
            "URL": "https://cdn.shopify.com/s/files/1/0302/2969/products/great-cookie-m_and_m-cookie-03_1024x1024.jpg?v=1390499314",
            "imageURL": "https://cdn.shopify.com/s/files/1/0302/2969/products/great-cookie-m_and_m-cookie-03_1024x1024.jpg?v=1390499314",
            "title": "candy cookie",
            "description": "m&m cookie",
            "timestamp": "tba"
        },
        "pin17": {
            "uid": "U4araoq24xMec8ukza0CFjznkvl2",
            "boardid": "board4",
            "URL": "https://s-media-cache-ak0.pinimg.com/736x/51/db/f4/51dbf4e1493d059dafbe5c54f18253fa.jpg",
            "imageURL": "https://s-media-cache-ak0.pinimg.com/736x/51/db/f4/51dbf4e1493d059dafbe5c54f18253fa.jpg",
            "title": "Fancy Cookies",
            "description": "decorated sugar cookies",
            "timestamp": "tba"
        },
        "pin18": {
            "uid": "U4araoq24xMec8ukza0CFjznkvl2",
            "boardid": "board4",
            "URL": "http://img1.southernliving.timeinc.net/sites/default/files/styles/story_card_two_thirds/public/image/2016/04/main/strawberry-dream-cake-2428901_0.jpg?itok=zbA9x4WX",
            "imageURL": "http://img1.southernliving.timeinc.net/sites/default/files/styles/story_card_two_thirds/public/image/2016/04/main/strawberry-dream-cake-2428901_0.jpg?itok=zbA9x4WX",
            "title": "Strawbery Cake",
            "description": "Yum!",
            "timestamp": "tba"
        },
        "pin19": {
            "uid": "U4araoq24xMec8ukza0CFjznkvl2",
            "boardid": "board4",
            "URL": "https://s-media-cache-ak0.pinimg.com/736x/29/ee/96/29ee96df49e02fae0ecd190bff81adbb.jpg",
            "imageURL": "https://s-media-cache-ak0.pinimg.com/736x/29/ee/96/29ee96df49e02fae0ecd190bff81adbb.jpg",
            "title": "Cherry Blossom Cake",
            "description": "so pretty!",
            "timestamp": "tba"
        },
        "pin20": {
            "uid": "U4araoq24xMec8ukza0CFjznkvl2",
            "boardid": "board5",
            "URL": "https://cdn.shopify.com/s/files/1/0302/2969/products/great-cookie-m_and_m-cookie-03_1024x1024.jpg?v=1390499314",
            "imageURL": "https://cdn.shopify.com/s/files/1/0302/2969/products/great-cookie-m_and_m-cookie-03_1024x1024.jpg?v=1390499314",
            "title": "candy cookie",
            "description": "m&m cookie",
            "timestamp": "tba"
        },
        "pin21": {
            "uid": "U4araoq24xMec8ukza0CFjznkvl2",
            "boardid": "board5",
            "URL": "https://s-media-cache-ak0.pinimg.com/736x/51/db/f4/51dbf4e1493d059dafbe5c54f18253fa.jpg",
            "imageURL": "https://s-media-cache-ak0.pinimg.com/736x/51/db/f4/51dbf4e1493d059dafbe5c54f18253fa.jpg",
            "title": "Fancy Cookies",
            "description": "decorated sugar cookies",
            "timestamp": "tba"
        },
        "pin22": {
            "uid": "U4araoq24xMec8ukza0CFjznkvl2",
            "boardid": "board5",
            "URL": "http://img1.southernliving.timeinc.net/sites/default/files/styles/story_card_two_thirds/public/image/2016/04/main/strawberry-dream-cake-2428901_0.jpg?itok=zbA9x4WX",
            "imageURL": "http://img1.southernliving.timeinc.net/sites/default/files/styles/story_card_two_thirds/public/image/2016/04/main/strawberry-dream-cake-2428901_0.jpg?itok=zbA9x4WX",
            "title": "Strawbery Cake",
            "description": "Yum!",
            "timestamp": "tba"
        },
        "pin23": {
            "uid": "U4araoq24xMec8ukza0CFjznkvl2",
            "boardid": "board5",
            "URL": "https://s-media-cache-ak0.pinimg.com/736x/29/ee/96/29ee96df49e02fae0ecd190bff81adbb.jpg",
            "imageURL": "https://s-media-cache-ak0.pinimg.com/736x/29/ee/96/29ee96df49e02fae0ecd190bff81adbb.jpg",
            "title": "Cherry Blossom Cake",
            "description": "so pretty!",
            "timestamp": "tba"
        },
        "pin24": {
            "uid": "oWJ7aGqItdRnfwtKSPlpdr4HI5K2",
            "boardid": "board6",
            "URL": "http://www.petmd.com/sites/default/files/what-to-feed-kitten.jpg",
            "imageURL": "http://www.petmd.com/sites/default/files/what-to-feed-kitten.jpg",
            "title": "milky",
            "description": "yum",
            "timestamp": "tba"
        },
        "pin25": {
            "uid": "oWJ7aGqItdRnfwtKSPlpdr4HI5K2",
            "boardid": "board6",
            "URL": "http://weknowyourdreams.com/images/kittens/kittens-07.jpg",
            "imageURL": "http://weknowyourdreams.com/images/kittens/kittens-07.jpg",
            "title": "mellow",
            "description": "marshy",
            "timestamp": "tba"
        },
        "pin26": {
            "uid": "oWJ7aGqItdRnfwtKSPlpdr4HI5K2",
            "boardid": "board6",
            "URL": "https://img0.etsystatic.com/014/0/6891295/il_340x270.418092714_tizq.jpg",
            "imageURL": "https://img0.etsystatic.com/014/0/6891295/il_340x270.418092714_tizq.jpg",
            "title": "kitten",
            "description": "hands",
            "timestamp": "tba"
        },
        "pin27": {
            "uid": "oWJ7aGqItdRnfwtKSPlpdr4HI5K2",
            "boardid": "board6",
            "URL": "https://cdn.notonthehighstreet.com/system/product_images/images/001/318/186/original_hidden-message-mittens.jpg",
            "imageURL": "https://cdn.notonthehighstreet.com/system/product_images/images/001/318/186/original_hidden-message-mittens.jpg",
            "title": "love",
            "description": "hands",
            "timestamp": "tba"
        },
        "pin28": {
            "uid": "oWJ7aGqItdRnfwtKSPlpdr4HI5K2",
            "boardid": "board7",
            "URL": "http://www.petmd.com/sites/default/files/what-to-feed-kitten.jpg",
            "imageURL": "http://www.petmd.com/sites/default/files/what-to-feed-kitten.jpg",
            "title": "milky",
            "description": "yum",
            "timestamp": "tba"
        },
        "pin29": {
            "uid": "oWJ7aGqItdRnfwtKSPlpdr4HI5K2",
            "boardid": "board7",
            "URL": "http://weknowyourdreams.com/images/kittens/kittens-07.jpg",
            "imageURL": "http://weknowyourdreams.com/images/kittens/kittens-07.jpg",
            "title": "mellow",
            "description": "marshy",
            "timestamp": "tba"
        },
        "pin30": {
            "uid": "oWJ7aGqItdRnfwtKSPlpdr4HI5K2",
            "boardid": "board7",
            "URL": "https://img0.etsystatic.com/014/0/6891295/il_340x270.418092714_tizq.jpg",
            "imageURL": "https://img0.etsystatic.com/014/0/6891295/il_340x270.418092714_tizq.jpg",
            "title": "kitten",
            "description": "hands",
            "timestamp": "tba"
        },
        "pin31": {
            "uid": "oWJ7aGqItdRnfwtKSPlpdr4HI5K2",
            "boardid": "board7",
            "URL": "https://cdn.notonthehighstreet.com/system/product_images/images/001/318/186/original_hidden-message-mittens.jpg",
            "imageURL": "https://cdn.notonthehighstreet.com/system/product_images/images/001/318/186/original_hidden-message-mittens.jpg",
            "title": "love",
            "description": "hands",
            "timestamp": "tba"
        },
         "pin32": {
            "uid": "AgVRquyOPkMNSxP1nqNhRz0ro8l1",
            "boardid": "global",
            "URL": " https://encrypted-tbn0.gstatic.com/images?q=tbn:ANd9GcRmGvyR8yMsNJ_G6BM3vQNxbuQdBC6HNGd0-fv2R0XqRwON_myJzw",
            "imageURL": " https://encrypted-tbn0.gstatic.com/images?q=tbn:ANd9GcRmGvyR8yMsNJ_G6BM3vQNxbuQdBC6HNGd0-fv2R0XqRwON_myJzw",
            "title": "rainbowed fractal",
            "description": "rainbowed fractal",
            "timestamp": "tba"
        },
        "pin33": {
            "uid": "AgVRquyOPkMNSxP1nqNhRz0ro8l1",
            "boardid": "global",
            "URL": "https://s-media-cache-ak0.pinimg.com/736x/c3/e7/27/c3e72742dfb048835c8389720942affe.jpg",
            "imageURL": "https://s-media-cache-ak0.pinimg.com/736x/c3/e7/27/c3e72742dfb048835c8389720942affe.jpg",
            "title": "umbrella fractal",
            "description": "umbrella fractal",
            "timestamp": "tba"
        },
        "pin34": {
            "uid": "AgVRquyOPkMNSxP1nqNhRz0ro8l1",
            "boardid": "global",
            "URL": "https://encrypted-tbn0.gstatic.com/images?q=tbn:ANd9GcRZvV4XaDg56nl0FgEOcZinEd5H7cnCxJ7tp_p8ts0-VrLKOih3",
            "imageURL": "https://encrypted-tbn0.gstatic.com/images?q=tbn:ANd9GcRZvV4XaDg56nl0FgEOcZinEd5H7cnCxJ7tp_p8ts0-VrLKOih3",
            "title": "snow fractal",
            "description": "snow fractal",
            "timestamp": "tba"
        },
        "pin35": {
            "uid": "AgVRquyOPkMNSxP1nqNhRz0ro8l1",
            "boardid": "global",
            "URL": "https://encrypted-tbn0.gstatic.com/images?q=tbn:ANd9GcRhRjBlxlj6v3pqzzfAcvPaLXASrmbWhZAYuTNSqrOpLg5z8NHG",
            "imageURL": "https://encrypted-tbn0.gstatic.com/images?q=tbn:ANd9GcRhRjBlxlj6v3pqzzfAcvPaLXASrmbWhZAYuTNSqrOpLg5z8NHG",
            "title": "web fractal",
            "description": "web fractal",
            "timestamp": "tba"
        },
        "pin36": {
            "uid": "Xo740wrxJHeybp7Qjk6Ax73AXzi1",
            "boardid": "global",
            "URL": "https://s-media-cache-ak0.pinimg.com/736x/79/d9/86/79d9862fb655c3c15a80078197bfa88f.jpg",
            "imageURL": "https://s-media-cache-ak0.pinimg.com/736x/79/d9/86/79d9862fb655c3c15a80078197bfa88f.jpg",
            "title": "Bug Kite",
            "description": "this guy is CRAZY!",
            "timestamp": "tba"
        },
        "pin37": {
            "uid": "Xo740wrxJHeybp7Qjk6Ax73AXzi1",
            "boardid": "global",
            "URL": "http://www.gkites.com/update/389-6.JPG",
            "imageURL": "http://www.gkites.com/update/389-6.JPG",
            "title": "Puppy Kites",
            "description": "lyk no wayz omg",
            "timestamp": "tba"
        },
        "pin38": {
            "uid": "Xo740wrxJHeybp7Qjk6Ax73AXzi1",
            "boardid": "global",
            "URL": "https://s-media-cache-ak0.pinimg.com/originals/ea/7e/22/ea7e2227edf4f2bd57379359aca731b4.jpg",
            "imageURL": "https://s-media-cache-ak0.pinimg.com/originals/ea/7e/22/ea7e2227edf4f2bd57379359aca731b4.jpg",
            "title": "purple lightning",
            "description": "scary pic of purple lightning (my fav color)",
            "timestamp": "tba"
        },
        "pin39": {
            "uid": "Xo740wrxJHeybp7Qjk6Ax73AXzi1",
            "boardid": "global",
            "URL": "https://dsx.weather.com//util/image/w/ef25fec9-b90d-4368-bb41-1da03aa2fe8e.jpg?v=at&w=1280&h=720&api=7db9fe61-7414-47b5-9871-e17d87b8b6a0",
            "imageURL": "https://dsx.weather.com//util/image/w/ef25fec9-b90d-4368-bb41-1da03aa2fe8e.jpg?v=at&w=1280&h=720&api=7db9fe61-7414-47b5-9871-e17d87b8b6a0",
            "title": "tree in the wind",
            "description": "wouldn't wanna be this guy!",
            "timestamp": "tba"
        },
        "pin40": {
            "uid": "U4araoq24xMec8ukza0CFjznkvl2",
            "boardid": "global",
            "URL": "https://cdn.shopify.com/s/files/1/0302/2969/products/great-cookie-m_and_m-cookie-03_1024x1024.jpg?v=1390499314",
            "imageURL": "https://cdn.shopify.com/s/files/1/0302/2969/products/great-cookie-m_and_m-cookie-03_1024x1024.jpg?v=1390499314",
            "title": "candy cookie",
            "description": "m&m cookie",
            "timestamp": "tba"
        },
        "pin41": {
            "uid": "U4araoq24xMec8ukza0CFjznkvl2",
            "boardid": "global",
            "URL": "https://s-media-cache-ak0.pinimg.com/736x/51/db/f4/51dbf4e1493d059dafbe5c54f18253fa.jpg",
            "imageURL": "https://s-media-cache-ak0.pinimg.com/736x/51/db/f4/51dbf4e1493d059dafbe5c54f18253fa.jpg",
            "title": "Fancy Cookies",
            "description": "decorated sugar cookies",
            "timestamp": "tba"
        },
        "pin42": {
            "uid": "U4araoq24xMec8ukza0CFjznkvl2",
            "boardid": "global",
            "URL": "http://img1.southernliving.timeinc.net/sites/default/files/styles/story_card_two_thirds/public/image/2016/04/main/strawberry-dream-cake-2428901_0.jpg?itok=zbA9x4WX",
            "imageURL": "http://img1.southernliving.timeinc.net/sites/default/files/styles/story_card_two_thirds/public/image/2016/04/main/strawberry-dream-cake-2428901_0.jpg?itok=zbA9x4WX",
            "title": "Strawbery Cake",
            "description": "Yum!",
            "timestamp": "tba"
        },
        "pin43": {
            "uid": "U4araoq24xMec8ukza0CFjznkvl2",
            "boardid": "global",
            "URL": "https://s-media-cache-ak0.pinimg.com/736x/29/ee/96/29ee96df49e02fae0ecd190bff81adbb.jpg",
            "imageURL": "https://s-media-cache-ak0.pinimg.com/736x/29/ee/96/29ee96df49e02fae0ecd190bff81adbb.jpg",
            "title": "Cherry Blossom Cake",
            "description": "so pretty!",
            "timestamp": "tba"
        },
        
        "pin44": {
            "uid": "oWJ7aGqItdRnfwtKSPlpdr4HI5K2",
            "boardid": "global",
            "URL": "http://www.petmd.com/sites/default/files/what-to-feed-kitten.jpg",
            "imageURL": "http://www.petmd.com/sites/default/files/what-to-feed-kitten.jpg",
            "title": "milky",
            "description": "yum",
            "timestamp": "tba"
        },
        "pin45": {
            "uid": "oWJ7aGqItdRnfwtKSPlpdr4HI5K2",
            "boardid": "global",
            "URL": "http://weknowyourdreams.com/images/kittens/kittens-07.jpg",
            "imageURL": "http://weknowyourdreams.com/images/kittens/kittens-07.jpg",
            "title": "mellow",
            "description": "marshy",
            "timestamp": "tba"
        },
        "pin46": {
            "uid": "oWJ7aGqItdRnfwtKSPlpdr4HI5K2",
            "boardid": "global",
            "URL": "https://img0.etsystatic.com/014/0/6891295/il_340x270.418092714_tizq.jpg",
            "imageURL": "https://img0.etsystatic.com/014/0/6891295/il_340x270.418092714_tizq.jpg",
            "title": "kitten",
            "description": "hands",
            "timestamp": "tba"
        },
        "pin47": {
            "uid": "oWJ7aGqItdRnfwtKSPlpdr4HI5K2",
            "boardid": "global",
            "URL": "https://cdn.notonthehighstreet.com/system/product_images/images/001/318/186/original_hidden-message-mittens.jpg",
            "imageURL": "https://cdn.notonthehighstreet.com/system/product_images/images/001/318/186/original_hidden-message-mittens.jpg",
            "title": "love",
            "description": "hands",
            "timestamp": "tba"
        }
    }
}
